binusmayapy/__init__.py
binusmayapy/bimay.py
binusmayapy/modules/__init__.py
binusmayapy/modules/academic_period.py
binusmayapy/modules/classes.py
binusmayapy/modules/forums.py
binusmayapy/modules/resources.py
binusmayapy/modules/schedules.py
binusmayapy/modules/token_grabber.py
binusmayapy/modules/user_profile.py
binusmayapy-1.0.1.dist-info/METADATA
binusmayapy-1.0.1.dist-info/WHEEL
binusmayapy-1.0.1.dist-info/top_level.txt
binusmayapy-1.0.1.dist-info/RECORD
