Metadata-Version: 2.1
Name: binusmayapy
Version: 1.0.1
Summary: Python wrapper for Binusmaya web API
Home-page: https://github.com/radityaharya/binusmaya_py
Author: Raditya Harya
Author-email: radityaharya02@gmail.com
Requires-Dist: python-dotenv
Requires-Dist: requests
Requires-Dist: selenium
Requires-Dist: selenium-wire
